cubicpy/__init__.py
cubicpy/api_method.py
cubicpy/app.py
cubicpy/axis.py
cubicpy/base_point.py
cubicpy/box.py
cubicpy/camera.py
cubicpy/cli.py
cubicpy/cone.py
cubicpy/cube.py
cubicpy/cubic_world.py
cubicpy/cylinder.py
cubicpy/draw_text.py
cubicpy/game_logic.py
cubicpy/geom_utils.py
cubicpy/input.py
cubicpy/input_handler.py
cubicpy/lighting.py
cubicpy/main.py
cubicpy/model_manager.py
cubicpy/physics.py
cubicpy/safe_exec.py
cubicpy/scene.py
cubicpy/sphere.py
cubicpy/transform.py
cubicpy/websocket.py
cubicpy/websocket_client.py
cubicpy/websocket_server.py
cubicpy/world_manager.py
cubicpy/examples/__init__.py
cubicpy/examples/box_building_sample.py
cubicpy/examples/box_cylinder_sample.py
cubicpy/examples/box_line_sample.py
cubicpy/examples/box_tower_sample.py
cubicpy/examples/column_building_2x2_sample.py
cubicpy/examples/column_building_3x3_sample.py
cubicpy/examples/cube_building_sample.py
cubicpy/examples/cube_cylinder_sample.py
cubicpy/examples/cube_tower_sample.py
cubicpy/examples/cylinder_line_sample.py
cubicpy/examples/cylinder_tower_sample.py
cubicpy/examples/delete_box_building_sample.py
cubicpy/examples/delete_box_tower_sample.py
cubicpy/examples/delete_column_building_2x2_sample.py
cubicpy/examples/delete_column_building_3x3_sample.py
cubicpy/examples/delete_cube_building_sample.py
cubicpy/examples/delete_cube_tower_sample.py
cubicpy/examples/falling_sphere_sample.py
cubicpy/examples/frame_building_2x2_sample.py
cubicpy/examples/frame_building_3x3_sample.py
cubicpy/examples/remove_cube_building_sample.py
cubicpy/examples/remove_cube_tower_sample.py
cubicpy/examples/remove_frame_building_2x2_sample.py
cubicpy/examples/remove_frame_building_3x3_sample.py
cubicpy/examples/sphere_line_sample.py
cubicpy/examples/sphere_tower_sample.py
cubicpy/examples/throwing_sphere_sample.py
cubicpy/font/PixelMplus10-Bold.ttf
cubicpy/font/PixelMplus10-Regular.ttf
cubicpy/font/PixelMplus12-Bold.ttf
cubicpy/font/PixelMplus12-Regular.ttf
cubicpy/models/box.egg
cubicpy-0.1.27.dist-info/LICENSE
cubicpy-0.1.27.dist-info/METADATA
cubicpy-0.1.27.dist-info/WHEEL
cubicpy-0.1.27.dist-info/entry_points.txt
cubicpy-0.1.27.dist-info/top_level.txt
cubicpy-0.1.27.dist-info/RECORD
