Metadata-Version: 2.1
Name: cubicpy
Version: 0.1.27
Summary: A Python library for creating 3D basic shape models and animations with Physics.
Home-page: https://github.com/creativival/CubicPy
Author: creativival
Author-email: creativival@gmail.com
Classifier: Programming Language :: Python :: 3
Classifier: License :: OSI Approved :: MIT License
Classifier: Intended Audience :: Education
Classifier: Topic :: Education :: Computer Aided Instruction (CAI)
Classifier: Operating System :: OS Independent
Requires-Python: >=3.9
License-File: LICENSE
Requires-Dist: panda3d
Requires-Dist: websockets
Requires-Dist: numpy
Requires-Dist: scipy
